envmix/__init__.py
envmix/model.py
envmix/py.typed
envmix-0.1.2.dist-info/WHEEL
envmix-0.1.2.dist-info/METADATA
envmix-0.1.2.dist-info/RECORD
