Metadata-Version: 2.3
Name: envmix
Version: 0.1.2
Summary: Pydantic v2 mixin to load settings from environment variables with robust casting
Keywords: pydantic,environment,config,settings,dotenv
License: MIT License
Classifier: Development Status :: 3 - Alpha
Classifier: Intended Audience :: Developers
Classifier: License :: OSI Approved :: MIT License
Classifier: Programming Language :: Python
Classifier: Programming Language :: Python :: 3
Classifier: Programming Language :: Python :: 3 :: Only
Classifier: Programming Language :: Python :: 3.9
Classifier: Programming Language :: Python :: 3.10
Classifier: Programming Language :: Python :: 3.11
Classifier: Programming Language :: Python :: 3.12
Classifier: Typing :: Typed
Requires-Dist: pydantic>=2.0
Requires-Dist: python-dotenv>=1.2.1
Requires-Python: >=3.9
Project-URL: Homepage, https://github.com/c0sogi/envmix
Project-URL: Issues, https://github.com/c0sogi/envmix/issues
